roco/__init__.py
roco/bin/cli.py
roco/config.py
roco/main.py
roco/templates/runtime-config.js.jinja2
roco-0.4.4.dist-info/LICENSE
roco-0.4.4.dist-info/METADATA
roco-0.4.4.dist-info/WHEEL
roco-0.4.4.dist-info/entry_points.txt
roco-0.4.4.dist-info/RECORD
