Metadata-Version: 2.1
Name: roco
Version: 0.4.4
Summary: Runtime Config Generator
Home-page: https://github.com/papermerge/roco
License: Apache 2.0
Author: Eugen Ciur
Author-email: eugen@papermerge.com
Requires-Python: >=3.10,<4.0
Classifier: License :: OSI Approved :: Apache Software License
Classifier: License :: Other/Proprietary License
Classifier: Operating System :: OS Independent
Classifier: Programming Language :: Python
Classifier: Programming Language :: Python :: 3
Classifier: Programming Language :: Python :: 3.10
Classifier: Programming Language :: Python :: 3.11
Classifier: Programming Language :: Python :: 3.12
Requires-Dist: jinja2 (>=3.1.2,<4.0.0)
Requires-Dist: pydantic (>=2.5,<3.0)
Requires-Dist: pydantic-settings (>=2.1.0,<3.0.0)
Requires-Dist: typer (>=0.9.0,<0.10.0)
